{
  "meta": {
    "updated_at": "2026-02-18T19:37:30.957783+09:00",
    "status": "success",
    "source": "FinanceDataReader"
  },
  "data": [
    {
      "name": "KOSPI",
      "symbol": "^KS11",
      "price": 5507.009765625,
      "change": -0.27634023422029885,
      "currency": "KRW",
      "status": "success"
    },
    {
      "name": "Gold",
      "symbol": "GC=F",
      "price": 4943.0,
      "change": 1.2308279681793697,
      "currency": "USD",
      "status": "success"
    },
    {
      "name": "Bitcoin",
      "symbol": "BTC-USD",
      "price": 67962.9296875,
      "change": 0.6944460520924246,
      "currency": "USD",
      "status": "success"
    },
    {
      "name": "NASDAQ",
      "symbol": "IXIC",
      "price": 22578.380859375,
      "change": 0.1406457699069508,
      "currency": "USD",
      "status": "success"
    }
  ]
}