{
  "meta": {
    "updated_at": "2026-02-20T21:41:33.021797+09:00",
    "status": "success",
    "source": "FinanceDataReader"
  },
  "data": [
    {
      "name": "KOSPI",
      "symbol": "^KS11",
      "price": 5808.52978515625,
      "change": 2.3123833749834866,
      "currency": "KRW",
      "status": "success"
    },
    {
      "name": "Gold",
      "symbol": "GC=F",
      "price": 5026.5,
      "change": 1.016903447603846,
      "currency": "USD",
      "status": "success"
    },
    {
      "name": "Bitcoin",
      "symbol": "BTC-USD",
      "price": 67420.8984375,
      "change": 0.6920432181643144,
      "currency": "USD",
      "status": "success"
    },
    {
      "name": "NASDAQ",
      "symbol": "IXIC",
      "price": 22682.73046875,
      "change": -0.3116003378238312,
      "currency": "USD",
      "status": "success"
    }
  ]
}