{
  "meta": {
    "updated_at": "2026-02-11T02:59:50.382203+09:00",
    "status": "success",
    "source": "FinanceDataReader"
  },
  "data": [
    {
      "name": "KOSPI",
      "symbol": "^KS11",
      "price": 5301.68994140625,
      "change": 0.068891558327971,
      "currency": "KRW",
      "status": "success"
    },
    {
      "name": "Gold",
      "symbol": "GC=F",
      "price": 5053.7998046875,
      "change": 0.05741357777461338,
      "currency": "USD",
      "status": "success"
    },
    {
      "name": "Bitcoin",
      "symbol": "BTC-USD",
      "price": 69712.7265625,
      "change": -0.5819311767864823,
      "currency": "USD",
      "status": "success"
    },
    {
      "name": "NASDAQ",
      "symbol": "IXIC",
      "price": 23257.78515625,
      "change": 0.08225614649746571,
      "currency": "USD",
      "status": "success"
    }
  ]
}